<?xml version="1.0"?>

<grouping>
	<width>11</width>
	<height>11</height>
	<ignoreplacementrules>1</ignoreplacementrules>
	<selectassingleunit>1</selectassingleunit>
	<units>
		<unit variation ="147" posx ="2.3699" posz ="-9.8977" orientx ="0.9239" orienty ="0.0000" orientz ="-0.3827">UnderbrushMongolia</unit>
		<unit variation ="206" posx ="-1.5618" posz ="-9.2521" orientx ="-0.1661" orienty ="0.0000" orientz ="-0.9861">ypSMSufiAccessory</unit>
		<unit variation ="188" posx ="1.4215" posz ="-9.3666" orientx ="-0.8338" orienty ="0.0000" orientz ="-0.5521">ypSMSufiAccessory</unit>
		<unit variation ="54" posx ="5.7265" posz ="-8.3375" orientx ="0.0000" orienty ="0.0000" orientz ="-1.0000">ypNativeTempleSufi</unit>
		<unit variation ="41" posx ="-4.9802" posz ="-5.3948" orientx ="0.0000" orienty ="0.0000" orientz ="-1.0000">ypSocketSufi</unit>
		<unit variation ="136" posx ="5.6806" posz ="-6.6873" orientx ="0.0000" orienty ="0.0000" orientz ="1.0000">ypNativeTempleSufi</unit>
		<unit variation ="213" posx ="3.5783" posz ="-8.4894" orientx ="-1.0000" orienty ="0.0000" orientz ="0.0000">ypNativeTempleSufi</unit>
		<unit variation ="246" posx ="2.0360" posz ="-5.5189" orientx ="0.0000" orienty ="0.0000" orientz ="-1.0000">NativeTownObstruction</unit>
		<unit variation ="190" posx ="0.3057" posz ="-6.8671" orientx ="0.9997" orienty ="0.0000" orientz ="0.0224">ypSMSufiMan</unit>
		<unit variation ="213" posx ="-0.8639" posz ="-4.0724" orientx ="0.0000" orienty ="0.0000" orientz ="1.0000">ypNativeTempleSufi</unit>
		<unit variation ="158" posx ="2.7517" posz ="-4.2405" orientx ="0.0000" orienty ="0.0000" orientz ="-1.0000">ypNativeTempleSufi</unit>
		<unit variation ="121" posx ="8.0202" posz ="-4.8574" orientx ="0.9239" orienty ="0.0000" orientz ="-0.3827">UnderbrushMongolia</unit>
		<unit variation ="196" posx ="4.6951" posz ="-5.0384" orientx ="-0.9685" orienty ="0.0000" orientz ="0.2489">ypSMSufiAccessory</unit>
		<unit variation ="136" posx ="-5.9538" posz ="-2.2310" orientx ="-1.0000" orienty ="0.0000" orientz ="0.0000">ypNativeTempleSufi</unit>
		<unit variation ="136" posx ="-2.6690" posz ="-2.2288" orientx ="-1.0000" orienty ="0.0000" orientz ="0.0000">ypNativeTempleSufi</unit>
		<unit variation ="213" posx ="5.7062" posz ="-3.6403" orientx ="0.0000" orienty ="0.0000" orientz ="1.0000">ypNativeTempleSufi</unit>
		<unit variation ="69" posx ="-9.2493" posz ="-3.2980" orientx ="-0.9608" orienty ="0.0000" orientz ="-0.2771">ypSMSufiAccessory</unit>
		<unit variation ="84" posx ="4.0373" posz ="-2.0676" orientx ="0.8214" orienty ="0.0000" orientz ="-0.5703">ypSMSufiAccessory</unit>
		<unit variation ="197" posx ="-7.9663" posz ="-0.3291" orientx ="0.0000" orienty ="0.0000" orientz ="-1.0000">ypNativeTempleSufi</unit>
		<unit variation ="220" posx ="-10.4322" posz ="-1.7319" orientx ="0.5496" orienty ="0.0000" orientz ="-0.8354">ypSMSufiAccessory</unit>
		<unit variation ="119" posx ="-9.4789" posz ="-1.6945" orientx ="0.0176" orienty ="0.0000" orientz ="-0.9998">ypSMSufiAccessory</unit>
		<unit variation ="86" posx ="2.2353" posz ="-1.8527" orientx ="-0.9988" orienty ="0.0000" orientz ="-0.0491">ypSMSufiAccessory</unit>
		<unit variation ="2" posx ="-4.5664" posz ="1.3466" orientx ="0.0000" orienty ="0.0000" orientz ="-1.0000">NativeTownObstruction</unit>
		<unit variation ="187" posx ="7.5999" posz ="0.3987" orientx ="-1.0000" orienty ="0.0000" orientz ="0.0000">ypNativeTempleSufi</unit>
		<unit variation ="158" posx ="3.1136" posz ="1.0200" orientx ="0.0000" orienty ="0.0000" orientz ="-1.0000">ypNativeTempleSufi</unit>
		<unit variation ="165" posx ="3.7338" posz ="0.8182" orientx ="0.0000" orienty ="0.0000" orientz ="-1.0000">ypNativeTempleSufi</unit>
		<unit variation ="224" posx ="-1.5553" posz ="0.3356" orientx ="0.0000" orienty ="0.0000" orientz ="-1.0000">ypNativeTempleSufi</unit>
		<unit variation ="119" posx ="-9.4718" posz ="1.6999" orientx ="-0.0364" orienty ="0.0000" orientz ="-0.9993">ypSMSufiAccessory</unit>
		<unit variation ="207" posx ="-2.6588" posz ="0.9771" orientx ="0.0216" orienty ="0.0000" orientz ="0.9998">ypSMSufiAccessory</unit>
		<unit variation ="54" posx ="4.4736" posz ="4.2846" orientx ="0.9239" orienty ="0.0000" orientz ="-0.3827">ypNativeTempleSufi</unit>
		<unit variation ="244" posx ="0.7238" posz ="3.2481" orientx ="0.0000" orienty ="0.0000" orientz ="-1.0000">UnderbrushBorneo</unit>
		<unit variation ="5" posx ="-9.4738" posz ="3.4040" orientx ="-0.4285" orienty ="0.0000" orientz ="-0.9035">ypSMSufiAccessory</unit>
		<unit variation ="71" posx ="-2.9761" posz ="3.6445" orientx ="0.9998" orienty ="0.0000" orientz ="0.0220">ypSMSufiAccessory</unit>
		<unit variation ="80" posx ="-5.9574" posz ="5.8132" orientx ="1.0000" orienty ="0.0000" orientz ="-0.0000">ypNativeTempleSufi</unit>
		<unit variation ="208" posx ="-0.5844" posz ="6.6405" orientx ="0.0000" orienty ="0.0000" orientz ="-1.0000">NativeTownObstruction</unit>
		<unit variation ="48" posx ="-9.3606" posz ="5.7092" orientx ="0.9239" orienty ="0.0000" orientz ="-0.3827">UnderbrushMongolia</unit>
		<unit variation ="87" posx ="-0.2240" posz ="6.7381" orientx ="0.9999" orienty ="0.0000" orientz ="0.0138">ypSMSufiGuy</unit>
		<unit variation ="54" posx ="-5.7117" posz ="8.6270" orientx ="0.0000" orienty ="0.0000" orientz ="-1.0000">ypNativeTempleSufi</unit>
	</units>
	<tiles>
		<tilegroup type ="PassableLand" subtype ="terrain\deccan\ground_dirt4_deccan">
			<block startx ="-5" startz ="-5" endx ="-5" endz ="-4"></block>
			<block startx ="-4" startz ="-5" endx ="-4" endz ="-4"></block>
			<block startx ="-5" startz ="-3" endx ="-5" endz ="4"></block>
			<block startx ="-4" startz ="-3" endx ="-4" endz ="4"></block>
			<block startx ="-3" startz ="-3" endx ="4" endz ="4"></block>
			<block startx ="-3" startz ="-5" endx ="-3" endz ="-4"></block>
			<block startx ="-2" startz ="-5" endx ="-2" endz ="-4"></block>
			<block startx ="-1" startz ="-5" endx ="-1" endz ="-4"></block>
			<block startx ="0" startz ="-5" endx ="0" endz ="-4"></block>
			<block startx ="1" startz ="-5" endx ="1" endz ="-4"></block>
			<block startx ="2" startz ="-5" endx ="2" endz ="-4"></block>
			<block startx ="3" startz ="-5" endx ="3" endz ="-4"></block>
			<block startx ="4" startz ="-5" endx ="4" endz ="-4"></block>
			<block startx ="-5" startz ="5" endx ="-5" endz ="5"></block>
			<block startx ="-4" startz ="5" endx ="-4" endz ="5"></block>
			<block startx ="-3" startz ="5" endx ="-3" endz ="5"></block>
			<block startx ="-2" startz ="5" endx ="-2" endz ="5"></block>
			<block startx ="-1" startz ="5" endx ="-1" endz ="5"></block>
			<block startx ="0" startz ="5" endx ="0" endz ="5"></block>
			<block startx ="1" startz ="5" endx ="1" endz ="5"></block>
			<block startx ="2" startz ="5" endx ="2" endz ="5"></block>
			<block startx ="3" startz ="5" endx ="3" endz ="5"></block>
			<block startx ="4" startz ="5" endx ="4" endz ="5"></block>
			<block startx ="5" startz ="5" endx ="5" endz ="5"></block>
			<block startx ="5" startz ="-5" endx ="5" endz ="-4"></block>
			<block startx ="5" startz ="-3" endx ="5" endz ="4"></block>
		</tilegroup>
		<heights>
			<tiles x ="-5" z ="-5">0.000 0.000 0.000 0.000 0.000 0.000 0.000 0.000 0.000 0.000 0.000 </tiles>
			<tiles x ="-5" z ="-4">0.000 0.000 0.000 0.000 0.000 0.000 0.000 0.000 0.000 0.000 0.000 </tiles>
			<tiles x ="-5" z ="-3">0.000 0.000 0.000 0.000 0.000 0.000 0.000 0.000 0.000 0.000 0.000 </tiles>
			<tiles x ="-5" z ="-2">0.000 0.000 0.000 0.000 0.000 0.000 0.000 0.000 0.000 0.000 0.000 </tiles>
			<tiles x ="-5" z ="-1">0.000 0.000 0.000 0.000 0.000 0.000 0.000 0.000 0.000 0.000 0.000 </tiles>
			<tiles x ="-5" z ="0">0.000 0.000 0.000 0.000 0.000 0.000 0.000 0.000 0.000 0.000 0.000 </tiles>
			<tiles x ="-5" z ="1">0.000 0.000 0.000 0.000 0.000 0.000 0.000 0.000 0.000 0.000 0.000 </tiles>
			<tiles x ="-5" z ="2">0.000 0.000 0.000 0.000 0.000 0.000 0.000 0.000 0.000 0.000 0.000 </tiles>
			<tiles x ="-5" z ="3">0.000 0.000 0.000 0.000 0.000 0.000 0.000 0.000 0.000 0.000 0.000 </tiles>
			<tiles x ="-5" z ="4">0.000 0.000 0.000 0.000 0.000 0.000 0.000 0.000 0.000 0.000 0.000 </tiles>
			<tiles x ="-5" z ="5">0.000 0.000 0.000 0.000 0.000 0.000 0.000 0.000 0.000 0.000 0.000 </tiles>
		</heights>
	</tiles>
</grouping>